aimcp/__init__.py
aimcp/_prompt.py
aimcp/aimcp.py
aimcp-0.1.2.dist-info/licenses/LICENSE
aimcp-0.1.2.dist-info/METADATA
aimcp-0.1.2.dist-info/WHEEL
aimcp-0.1.2.dist-info/top_level.txt
aimcp-0.1.2.dist-info/RECORD
