Metadata-Version: 2.4
Name: aimcp
Version: 0.1.2
Summary: AI-Enhanced MCP Tool Manager with intelligent tool description generation
Author-email: zh <xiaohaina163@gmail.com>
Maintainer-email: zh <xiaohaina163@gmail.com>
License: MIT
Project-URL: Homepage, https://github.com/llmadd/aimcp
Project-URL: Repository, https://github.com/llmadd/aimcp
Project-URL: Documentation, https://github.com/llmadd/aimcp#readme
Project-URL: Bug Tracker, https://github.com/llmadd/aimcp/issues
Keywords: mcp,ai,tools,openai,model-context-protocol
Classifier: Development Status :: 3 - Alpha
Classifier: Intended Audience :: Developers
Classifier: Operating System :: OS Independent
Classifier: Programming Language :: Python :: 3
Classifier: Programming Language :: Python :: 3.8
Classifier: Programming Language :: Python :: 3.9
Classifier: Programming Language :: Python :: 3.10
Classifier: Programming Language :: Python :: 3.11
Classifier: Programming Language :: Python :: 3.12
Classifier: Topic :: Software Development :: Libraries :: Python Modules
Classifier: Topic :: Scientific/Engineering :: Artificial Intelligence
Requires-Python: >=3.8
License-File: LICENSE
Requires-Dist: fastmcp>=0.1.0
Requires-Dist: openai>=1.0.0
Requires-Dist: pydantic>=2.0.0
Provides-Extra: dev
Requires-Dist: pytest>=6.0; extra == "dev"
Requires-Dist: pytest-asyncio; extra == "dev"
Requires-Dist: black; extra == "dev"
Requires-Dist: isort; extra == "dev"
Requires-Dist: flake8; extra == "dev"
Requires-Dist: mypy; extra == "dev"
Dynamic: license-file
